pytrpp/__init__.py
pytrpp/__main__.py
pytrpp/api.py
pytrpp/conv.py
pytrpp/main.py
pytrpp/trdl.py
pytrpp-0.4.2.dist-info/licenses/LICENSE
pytrpp-0.4.2.dist-info/METADATA
pytrpp-0.4.2.dist-info/WHEEL
pytrpp-0.4.2.dist-info/entry_points.txt
pytrpp-0.4.2.dist-info/top_level.txt
pytrpp-0.4.2.dist-info/zip-safe
pytrpp-0.4.2.dist-info/RECORD
