Metadata-Version: 2.4
Name: pytrpp
Version: 0.4.2
Summary: Download TradeRepublic files and convert data for import in Portfolio Performance.
Home-page: https://github.com/martinscharrer/pytrpp/
Author: Martin Scharrer
Author-email: martin.scharrer@web.de
License: MIT
Classifier: License :: OSI Approved :: MIT License
Classifier: Programming Language :: Python :: 3 :: Only
Classifier: Operating System :: OS Independent
Classifier: Development Status :: 4 - Beta
Classifier: Topic :: Office/Business :: Financial
Classifier: Topic :: Office/Business :: Financial :: Investment
Requires-Python: >=3.12
License-File: LICENSE
Requires-Dist: certifi
Requires-Dist: coloredlogs
Requires-Dist: ecdsa
Requires-Dist: packaging
Requires-Dist: pathvalidate
Requires-Dist: pygments
Requires-Dist: requests_futures
Requires-Dist: shtab
Requires-Dist: websockets>=15.0
Dynamic: author
Dynamic: author-email
Dynamic: classifier
Dynamic: description
Dynamic: description-content-type
Dynamic: home-page
Dynamic: license
Dynamic: license-file
Dynamic: requires-dist
Dynamic: requires-python
Dynamic: summary
